chessboard/__init__.py
chessboard/benchmark.py
chessboard/board.py
chessboard/cli.py
chessboard/pieces.py
chessboard/solver.py
chessboard/tests/__init__.py
chessboard/tests/test_board.py
chessboard/tests/test_pieces.py
chessboard/tests/test_solver.py
chessboard-1.5.4.dist-info/DESCRIPTION.rst
chessboard-1.5.4.dist-info/METADATA
chessboard-1.5.4.dist-info/RECORD
chessboard-1.5.4.dist-info/WHEEL
chessboard-1.5.4.dist-info/entry_points.txt
chessboard-1.5.4.dist-info/metadata.json
chessboard-1.5.4.dist-info/top_level.txt
