Metadata-Version: 2.0
Name: chessboard
Version: 1.5.4
Summary: CLI to solve combinatoric chess puzzles.
Home-page: https://github.com/kdeldycke/chessboard
Author: Kevin Deldycke
Author-email: kevin@deldycke.com
License: GPLv2+
Keywords: chess,puzzle,CLI,solver
Platform: UNKNOWN
Classifier: Development Status :: 5 - Production/Stable
Classifier: Environment :: Console
Classifier: Intended Audience :: Developers
Classifier: Intended Audience :: Science/Research
Classifier: License :: OSI Approved :: GNU General Public License v2 or later (GPLv2+)
Classifier: Operating System :: OS Independent
Classifier: Programming Language :: Python
Classifier: Programming Language :: Python :: 2
Classifier: Programming Language :: Python :: 2.7
Classifier: Programming Language :: Python :: 3
Classifier: Programming Language :: Python :: 3.3
Classifier: Programming Language :: Python :: 3.4
Classifier: Programming Language :: Python :: 3.5
Classifier: Programming Language :: Python :: 3.6
Classifier: Programming Language :: Python :: Implementation :: CPython
Classifier: Topic :: Education
Classifier: Topic :: Games/Entertainment :: Board Games
Requires-Python: >= 2.7, != 3.0.*, != 3.1.*, != 3.2.*
Requires-Dist: bprofile
Requires-Dist: click (>=5.0)
Requires-Dist: click-log
Requires-Dist: numpy
Requires-Dist: pandas
Requires-Dist: py-cpuinfo
Requires-Dist: seaborn
Provides-Extra: develop
Requires-Dist: bumpversion; extra == 'develop'
Requires-Dist: isort; extra == 'develop'
Requires-Dist: readme-renderer (>=16.0); extra == 'develop'
Requires-Dist: setuptools (>=24.2.1); extra == 'develop'
Requires-Dist: wheel; extra == 'develop'
Provides-Extra: docs
Requires-Dist: sphinx (>=1.4); extra == 'docs'
Requires-Dist: sphinx-rtd-theme; extra == 'docs'
Provides-Extra: tests
Requires-Dist: coverage; extra == 'tests'
Requires-Dist: nose; extra == 'tests'
Requires-Dist: pipdeptree[graphviz]; extra == 'tests'
Requires-Dist: pycodestyle (>=2.1.0); extra == 'tests'
Requires-Dist: pylint; extra == 'tests'
